mcp_server_pacman/__init__.py
mcp_server_pacman/__main__.py
mcp_server_pacman/server.py
mcp_server_pacman/models/__init__.py
mcp_server_pacman/models/package_models.py
mcp_server_pacman/providers/__init__.py
mcp_server_pacman/providers/crates.py
mcp_server_pacman/providers/dockerhub.py
mcp_server_pacman/providers/npm.py
mcp_server_pacman/providers/pypi.py
mcp_server_pacman/providers/terraform.py
mcp_server_pacman/utils/__init__.py
mcp_server_pacman/utils/cache.py
mcp_server_pacman/utils/constants.py
mcp_server_pacman/utils/parsers.py
mseep_mcp_server_pacman-0.2.1.dist-info/licenses/LICENSE
mseep_mcp_server_pacman-0.2.1.dist-info/METADATA
mseep_mcp_server_pacman-0.2.1.dist-info/WHEEL
mseep_mcp_server_pacman-0.2.1.dist-info/entry_points.txt
mseep_mcp_server_pacman-0.2.1.dist-info/top_level.txt
mseep_mcp_server_pacman-0.2.1.dist-info/RECORD
