Metadata-Version: 2.4
Name: mseep-mcp-server-pacman
Version: 0.2.1
Summary: A Model Context Protocol server providing tools to query package indices like PyPI, npm, and crates.io
Author-email: mseep <support@skydeck.ai>
License: MIT
Keywords: pypi,npm,crates,mcp,llm,automation
Classifier: Development Status :: 4 - Beta
Classifier: Intended Audience :: Developers
Classifier: License :: OSI Approved :: MIT License
Classifier: Programming Language :: Python :: 3
Classifier: Programming Language :: Python :: 3.11
Requires-Python: >=3.11
License-File: LICENSE
Requires-Dist: httpx<0.28
Requires-Dist: mcp>=1.1.3
Requires-Dist: pydantic>=2.0.0
Requires-Dist: cachetools>=5.3.0
Requires-Dist: loguru>=0.7.3
Dynamic: license-file
